<annotation>
  <folder>images</folder>
  <filename>1012.jpg</filename>
  <path>object_detection_demo/images/1012.jpg</path>
  <source>
    <database>Unknown</database>
  </source>
  <size>
    <width>800</width>
    <height>600</height>
    <depth>3</depth>
  </size>
  <segmented>0</segmented>
  <object>
    <name>Button</name>
    <pose>Unspecified</pose>
    <truncated>0</truncated>
    <difficult>0</difficult>
    <bndbox>
      <xmin>10</xmin>
      <xmax>85</xmax>
      <ymin>15</ymin>
      <ymax>55</ymax>
    </bndbox>
  </object>
  <object>
    <name>Input</name>
    <pose>Unspecified</pose>
    <truncated>0</truncated>
    <difficult>0</difficult>
    <bndbox>
      <xmin>36</xmin>
      <xmax>764</xmax>
      <ymin>162</ymin>
      <ymax>189</ymax>
    </bndbox>
  </object>
  <object>
    <name>Input</name>
    <pose>Unspecified</pose>
    <truncated>0</truncated>
    <difficult>0</difficult>
    <bndbox>
      <xmin>36</xmin>
      <xmax>764</xmax>
      <ymin>194</ymin>
      <ymax>220</ymax>
    </bndbox>
  </object>
  <object>
    <name>Input</name>
    <pose>Unspecified</pose>
    <truncated>0</truncated>
    <difficult>0</difficult>
    <bndbox>
      <xmin>36</xmin>
      <xmax>764</xmax>
      <ymin>225</ymin>
      <ymax>252</ymax>
    </bndbox>
  </object>
  <object>
    <name>Input</name>
    <pose>Unspecified</pose>
    <truncated>0</truncated>
    <difficult>0</difficult>
    <bndbox>
      <xmin>36</xmin>
      <xmax>764</xmax>
      <ymin>257</ymin>
      <ymax>284</ymax>
    </bndbox>
  </object>
</annotation>
