<annotation>
  <folder>images</folder>
  <filename>1119.jpg</filename>
  <path>object_detection_demo/images/1119.jpg</path>
  <source>
    <database>Unknown</database>
  </source>
  <size>
    <width>800</width>
    <height>600</height>
    <depth>3</depth>
  </size>
  <segmented>0</segmented>
  <object>
    <name>Button</name>
    <pose>Unspecified</pose>
    <truncated>0</truncated>
    <difficult>0</difficult>
    <bndbox>
      <xmin>0</xmin>
      <xmax>85</xmax>
      <ymin>15</ymin>
      <ymax>54</ymax>
    </bndbox>
  </object>
  <object>
    <name>Button</name>
    <pose>Unspecified</pose>
    <truncated>0</truncated>
    <difficult>0</difficult>
    <bndbox>
      <xmin>266</xmin>
      <xmax>533</xmax>
      <ymin>365</ymin>
      <ymax>395</ymax>
    </bndbox>
  </object>
  <object>
    <name>Input</name>
    <pose>Unspecified</pose>
    <truncated>0</truncated>
    <difficult>0</difficult>
    <bndbox>
      <xmin>66</xmin>
      <xmax>733</xmax>
      <ymin>289</ymin>
      <ymax>315</ymax>
    </bndbox>
  </object>
</annotation>
