<annotation>
	<folder>images</folder>
	<filename>15.jpg</filename>
	<path>/home/abhishek/cn/data/images/15.jpg</path>
	<source>
		<database>Unknown</database>
	</source>
	<size>
		<width>800</width>
		<height>600</height>
		<depth>3</depth>
	</size>
	<segmented>0</segmented>
	<object>
		<name>input</name>
		<pose>Unspecified</pose>
		<truncated>0</truncated>
		<difficult>0</difficult>
		<bndbox>
			<xmin>331</xmin>
			<ymin>134</ymin>
			<xmax>469</xmax>
			<ymax>167</ymax>
		</bndbox>
	</object>
	<object>
		<name>input</name>
		<pose>Unspecified</pose>
		<truncated>0</truncated>
		<difficult>0</difficult>
		<bndbox>
			<xmin>331</xmin>
			<ymin>177</ymin>
			<xmax>470</xmax>
			<ymax>207</ymax>
		</bndbox>
	</object>
	<object>
		<name>button</name>
		<pose>Unspecified</pose>
		<truncated>0</truncated>
		<difficult>0</difficult>
		<bndbox>
			<xmin>331</xmin>
			<ymin>233</ymin>
			<xmax>468</xmax>
			<ymax>264</ymax>
		</bndbox>
	</object>
</annotation>
