<annotation>
  <folder>images</folder>
  <filename>2054.jpg</filename>
  <path>object_detection_demo/images/2054.jpg</path>
  <source>
    <database>Unknown</database>
  </source>
  <size>
    <width>800</width>
    <height>600</height>
    <depth>3</depth>
  </size>
  <segmented>0</segmented>
  <object>
    <name>Button</name>
    <pose>Unspecified</pose>
    <truncated>0</truncated>
    <difficult>0</difficult>
    <bndbox>
      <xmin>509</xmin>
      <xmax>608</xmax>
      <ymin>30</ymin>
      <ymax>57</ymax>
    </bndbox>
  </object>
  <object>
    <name>Button</name>
    <pose>Unspecified</pose>
    <truncated>0</truncated>
    <difficult>0</difficult>
    <bndbox>
      <xmin>609</xmin>
      <xmax>708</xmax>
      <ymin>30</ymin>
      <ymax>57</ymax>
    </bndbox>
  </object>
  <object>
    <name>Button</name>
    <pose>Unspecified</pose>
    <truncated>0</truncated>
    <difficult>0</difficult>
    <bndbox>
      <xmin>722</xmin>
      <xmax>791</xmax>
      <ymin>534</ymin>
      <ymax>566</ymax>
    </bndbox>
  </object>
  <object>
    <name>Input</name>
    <pose>Unspecified</pose>
    <truncated>0</truncated>
    <difficult>0</difficult>
    <bndbox>
      <xmin>145</xmin>
      <xmax>509</xmax>
      <ymin>30</ymin>
      <ymax>57</ymax>
    </bndbox>
  </object>
</annotation>
