<annotation>
  <folder>images</folder>
  <filename>647.jpg</filename>
  <path>object_detection_demo/images/647.jpg</path>
  <source>
    <database>Unknown</database>
  </source>
  <size>
    <width>800</width>
    <height>600</height>
    <depth>3</depth>
  </size>
  <segmented>0</segmented>
  <object>
    <name>Input</name>
    <pose>Unspecified</pose>
    <truncated>0</truncated>
    <difficult>0</difficult>
    <bndbox>
      <xmin>41</xmin>
      <xmax>760</xmax>
      <ymin>118</ymin>
      <ymax>140</ymax>
    </bndbox>
  </object>
</annotation>
